brightdata/__init__.py
brightdata/auto.py
brightdata/client.py
brightdata/config.py
brightdata/constants.py
brightdata/models.py
brightdata/payloads.py
brightdata/protocols.py
brightdata/py.typed
brightdata/sync_client.py
brightdata/types.py
brightdata/_internal/__init__.py
brightdata/_internal/compat.py
brightdata/api/__init__.py
brightdata/api/async_unblocker.py
brightdata/api/base.py
brightdata/api/crawl.py
brightdata/api/crawler_service.py
brightdata/api/datasets.py
brightdata/api/download.py
brightdata/api/scrape_service.py
brightdata/api/search_service.py
brightdata/api/web_unlocker.py
brightdata/api/browser/__init__.py
brightdata/api/browser/browser_api.py
brightdata/api/browser/browser_pool.py
brightdata/api/browser/config.py
brightdata/api/browser/session.py
brightdata/api/serp/__init__.py
brightdata/api/serp/base.py
brightdata/api/serp/bing.py
brightdata/api/serp/data_normalizer.py
brightdata/api/serp/google.py
brightdata/api/serp/url_builder.py
brightdata/api/serp/yandex.py
brightdata/cli/__init__.py
brightdata/cli/banner.py
brightdata/cli/main.py
brightdata/cli/utils.py
brightdata/cli/commands/__init__.py
brightdata/cli/commands/scrape.py
brightdata/cli/commands/search.py
brightdata/core/__init__.py
brightdata/core/auth.py
brightdata/core/engine.py
brightdata/core/hooks.py
brightdata/core/logging.py
brightdata/core/zone_manager.py
brightdata/exceptions/__init__.py
brightdata/exceptions/errors.py
brightdata/scrapers/__init__.py
brightdata/scrapers/api_client.py
brightdata/scrapers/base.py
brightdata/scrapers/job.py
brightdata/scrapers/registry.py
brightdata/scrapers/workflow.py
brightdata/scrapers/amazon/__init__.py
brightdata/scrapers/amazon/scraper.py
brightdata/scrapers/amazon/search.py
brightdata/scrapers/chatgpt/__init__.py
brightdata/scrapers/chatgpt/scraper.py
brightdata/scrapers/chatgpt/search.py
brightdata/scrapers/facebook/__init__.py
brightdata/scrapers/facebook/scraper.py
brightdata/scrapers/instagram/__init__.py
brightdata_sdk-2.1.1.dist-info/licenses/LICENSE
brightdata_sdk-2.1.1.dist-info/METADATA
brightdata_sdk-2.1.1.dist-info/WHEEL
brightdata_sdk-2.1.1.dist-info/entry_points.txt
brightdata_sdk-2.1.1.dist-info/top_level.txt
brightdata_sdk-2.1.1.dist-info/RECORD
