Metadata-Version: 2.4
Name: brightdata-sdk
Version: 2.1.1
Summary: Modern async-first Python SDK for Bright Data APIs
Home-page: https://github.com/brightdata/sdk-python
Author: Bright Data
Author-email: Bright Data <support@brightdata.com>
License: MIT
Requires-Python: >=3.9
License-File: LICENSE
Requires-Dist: aiohttp>=3.9.0
Requires-Dist: requests>=2.31.0
Requires-Dist: python-dotenv>=1.0.0
Requires-Dist: tldextract>=5.0.0
Requires-Dist: pydantic>=2.0.0
Requires-Dist: pydantic-settings>=2.0.0
Requires-Dist: aiolimiter>=1.1.0
Requires-Dist: click>=8.1.0
Provides-Extra: dev
Requires-Dist: pytest>=7.4.0; extra == "dev"
Requires-Dist: pytest-asyncio>=0.21.0; extra == "dev"
Requires-Dist: pytest-cov>=4.1.0; extra == "dev"
Requires-Dist: pytest-mock>=3.11.0; extra == "dev"
Requires-Dist: black>=23.0.0; extra == "dev"
Requires-Dist: ruff>=0.1.0; extra == "dev"
Requires-Dist: mypy>=1.5.0; extra == "dev"
Requires-Dist: pre-commit>=3.4.0; extra == "dev"
Provides-Extra: browser
Requires-Dist: playwright>=1.40.0; extra == "browser"
Provides-Extra: all
Requires-Dist: brightdata-sdk[browser,dev]; extra == "all"
Dynamic: author
Dynamic: home-page
Dynamic: license-file
Dynamic: requires-python
